setup.py
zfx_textutils/__init__.py
zfx_textutils/从中间往右取.py
zfx_textutils/从中间往左取.py
zfx_textutils/从右往左取.py
zfx_textutils/从左往右取.py
zfx_textutils/分割文本.py
zfx_textutils/到大写.py
zfx_textutils/到小写.py
zfx_textutils/加密.py
zfx_textutils/十六进制替换.py
zfx_textutils/去除尾空.py
zfx_textutils/去除指定字符串_末次出现.py
zfx_textutils/去除指定字符串_自定义位置.py
zfx_textutils/去除指定字符串_首次出现.py
zfx_textutils/去除换行符.py
zfx_textutils/去除空格.py
zfx_textutils/去除空格和换行符.py
zfx_textutils/去除首尾空.py
zfx_textutils/去除首空.py
zfx_textutils/取出中间文本.py
zfx_textutils/取出现次数.py
zfx_textutils/取右边.py
zfx_textutils/取左边.py
zfx_textutils/取指定变量文本行.py
zfx_textutils/取文本所在行.py
zfx_textutils/取文本指定次数出现的位置.py
zfx_textutils/取文本最后出现的位置.py
zfx_textutils/取文本首次出现的位置.py
zfx_textutils/取行数.py
zfx_textutils/取长度.py
zfx_textutils/取随机字符.py
zfx_textutils/取随机范围数字.py
zfx_textutils/只取数字.py
zfx_textutils/只取汉字.py
zfx_textutils/只取符号.py
zfx_textutils/字符串替换.py
zfx_textutils/微软方式加密邮箱.py
zfx_textutils/替换行内容.py
zfx_textutils/生成随机密码.py
zfx_textutils/解密.py
zfx_textutils/颠倒.py
zfx_textutils.egg-info/PKG-INFO
zfx_textutils.egg-info/SOURCES.txt
zfx_textutils.egg-info/dependency_links.txt
zfx_textutils.egg-info/top_level.txt